QZFM/LabJack.py
QZFM/QZFM.py
QZFM/__init__.py
QZFM-0.2.0.dist-info/LICENSE
QZFM-0.2.0.dist-info/METADATA
QZFM-0.2.0.dist-info/WHEEL
QZFM-0.2.0.dist-info/top_level.txt
QZFM-0.2.0.dist-info/RECORD
