Metadata-Version: 2.1
Name: QZFM
Version: 0.2.0
Summary: Python class for serial communication with QuSpin Zero Field Magnetometer
Author-email: Derek Fujimoto <dfujimoto@triumf.ca>
Project-URL: Homepage, https://github.com/ucn-triumf/QZFM
Project-URL: Bug Tracker, https://github.com/ucn-triumf/QZFM/issues
Keywords: QZFM,QuSpin,Magnetometer,Zero Field
Classifier: Programming Language :: Python :: 3
Classifier: License :: OSI Approved :: MIT License
Classifier: Operating System :: OS Independent
Requires-Python: >=3.7
License-File: LICENSE
Requires-Dist: numpy
Requires-Dist: matplotlib
Requires-Dist: pyserial
Requires-Dist: datetime
Requires-Dist: tqdm
Requires-Dist: pandas
Requires-Dist: plotext
